Metadata-Version: 1.0
Name: mmmanip
Version: 0.1a2dev
Summary: Tools for manipulating a mailman list (subscribe, query, remove) via HTTP
Home-page: http://github.com/ralphbean/mmmanip
Author: Ralph Bean
Author-email: ralph.bean@gmail.com
License: GPLv3+
Platform: UNKNOWN
Classifier: Development Status :: 3 - Alpha
Classifier: Topic :: Software Development :: Libraries :: Python Modules
